{
  "folder": "IC-132",
  "content": "{{knowledge objective\n|Identifiant=OIC-132-05-A\n|Item_parent=Cognitive disorders in the elderly. (see item 108)\n|Item_parent_short=Cognitive disorders in the elderly. (see item 108)\n|Rank=A\n|Title=Know the differential diagnoses of Alzheimer's disease and related disorders.\n|Description=Know the curable diseases that can lead to neuro-cognitive disorders.\n|Rubric=Positive diagnosis\n|Contributors=\n|Order=5}}\nThere are medical conditions that can lead to neuro-cognitive disorders that are possibly/partially reversible with appropriate treatment:\n\n\n- Vitamin deficiencies (B12, B9)\n\n- Subdural haematoma\n\n- Intracranial tumour\n\n- Hydrocephalus at normal pressure\n\n- Carbon monoxide poisoning (damage to the basal ganglia)\n\n- Endocrine disorders (hypothyroidism, chronic adrenal insufficiency)\n\n- Hyponatraemia/hypercalcaemia of progressive onset\n\n- Iatrogenicity: drug encephalopathy (valproate, lithium, etc.), anticholinergic drugs, psychotropic drugs, etc.\n\n- Systemic inflammatory diseases (vasculitis, etc.)\n\n- Paraneoplastic syndromes\n\n- Infections (neurosyphilis, HIV...)\n\n- ...\n\n<br />",
  "question": {
    "question": "Which of the following conditions is NOT typically considered a reversible cause of neuro-cognitive disorders when properly treated?",
    "option_a": "Vitamin B12 deficiency",
    "option_b": "Subdural haematoma",
    "option_c": "Intracranial tumour",
    "option_d": "Carbon monoxide poisoning",
    "correct_option": "C"
  }
}