{
  "folder": "IC-351",
  "content": "{{knowledge objective\n|Identifiant=OIC-351-02-A\n|Item_parent=Agitation and acute delirium\n|Item_parent_short=Agitation and acute delirium\n|Rank=A\n|Title=Know the definition of delusions and hallucinations\n|Description=None\n|Rubric=Definition\n|Contributors=\n|Order=2}}\n'''[[Delusional Ideas SD-124|Delusional Ideas]] :'''' Alterations in the content of thought leading to a loss of contact with reality, not shared by the socio-cultural group.\n\n'''[[Hallucinations SD-122|Hallucinations]]:''' Sensory perception without the presence of a detectable object.",
  "question": {
    "properties": {
      "question": "What are delusions and hallucinations as defined in the context of Agitation and acute delirium?",
      "option_a": "Emotional responses to stressful situations",
      "option_b": "Alterations in thought leading to a loss of contact with reality",
      "option_c": "Physical symptoms experienced during acute illness",
      "option_d": "Behavioral changes due to environmental factors",
      "correct_option": "b"
    },
    "required": [
      "question",
      "option_a",
      "option_b",
      "option_c",
      "option_d",
      "correct_option"
    ]
  }
}