{
  "folder": "IC-364",
  "content": "{{knowledge objective\n|Identifiant=OIC-364-08-B\n|Item_parent=Fractures in children: epidemiological, diagnostic and therapeutic features\n|Item_parent_short=Fractures in children: epidemiological, diagnostic and therapeutic features\n|Rank=B\n|Title=Know the principles of management of fractures in children\n|Description=Know the risks of cast immobilisation\n|Rubric=Management\n|Contributors=\n|Order=8}}\nTo know the therapeutic principles of fractures in children: orthopaedic treatment and its monitoring, surgical treatment and its monitoring. Know that osteosynthesis in children differs from that in adults. Know that the growth plate must be rigorously preserved during osteosynthesis in children. Know that plaster cast immobilisation is well tolerated in children and that it is also used after osteosynthesis. Know that there is no indication for physiotherapy after plaster cast immobilisation for fractures in children.",
  "question": {
    "question": "What is a common practice in the management of fractures in children after osteosynthesis?",
    "option_a": "Physiotherapy is always required to prevent stiffness",
    "option_b": "Plaster cast immobilisation is used to allow the fracture to heal undisturbed",
    "option_c": "Surgical treatment is always preferred over orthopaedic treatment",
    "option_d": "Osteosynthesis in children is performed without any consideration for the growth plate",
    "correct_option": "B"
  }
}