{
  "folder": "IC-234",
  "content": "{{knowledge objective\n|Identifiant=OIC-234-16-A\n|Item_parent=Adult heart failure\n|Item_parent_short=Adult heart failure\n|Rank=A\n|Title=Knowing the main causes of heart failure\n|Description=Know the main causes of left heart failure (ischaemic heart disease, hypertension, valvular heart disease, cardiomyopathy, rhythmic heart disease).\n|Rubric=Etiologies\n|Contributors=Olivier Huttin\n|Order=16}}\n'''Etiologies of left heart failure'''\n<br />\n\n====== '''Ischaemic heart disease''' ======\n- With or without sequelae of myocardial infarction,\n\n- Ventricular dysfunction in ischaemic but viable myocardium may be reversible after revascularisation (notion of myocardial sideration).\n\n====== '''HTA''' ======\n- frequently implicated in heart failure with preserved ejection fraction\n<br />\n\n====== '''Valvulopathies''' ======\nAll severe valvulopathies can be complicated by heart failure.\n\n====== '''Cardiomyopathies''' ======\n- dilated\n\no primary: no cause found (diagnosis of elimination)\n\no familial: in 25% of cases, related to a monogenic disease (mutation in a gene).\n\no toxic (alcohol, drugs such as cocaine);\n\no myocarditis (infectious, autoimmune) in the acute or sequelae phase\n\no endocrine (dysthyroidism, etc.); nutritional (thiamine deficiency); metabolic (haemochromatosis)\n\no pregnancy (post-partum cardiomyopathy) ;\n\no drugs, chemotherapy (anthracycline, herceptin).\n\n- hypertrophic cardiomyopathies: sarcomeric, infiltrative (amyloidosis, Fabry disease)\n\n- restrictive cardiomyopathies: cardiac amyloidosis, haemochromatosis, post-radiotherapy\n<br />\n\n====== '''Supra ventricular and ventricular rhythm disorders''' ======\ncausing heart failure or triggering factors.\n<br />\n\n====== '''Pericardial causes''' ======\nAbundant pericardial effusion, tamponade, chronic constrictive pericarditis.\n\n====== '''Specific causes of right heart failure''' ======\n- left heart failure most common cause = congestive heart failure.\n\n- Chronic respiratory insufficiency\n\n- pre-capillary pulmonary arterial hypertension and its causes: pulmonary embolism, anorectics, porto-pulmonary PAH, paraneoplastic, veno-occlusive and primary diseases, etc.\n\n- arrhythmogenic right ventricular dysplasia\n\n- tricuspid valve disease\n\n- right ventricular infarction;\n\n- chronic constrictive pericarditis\n\n\n====== '''Triggering factors''' ======\n- Atrial fibrillation (AF) and other rhythm disorders\n\n- Hypertensive flare-up\n\n- Myocardial ischaemia / Acute coronary syndrome (ACS)\n\n- Infections\n\n- Pulmonary embolism (PE)\n\n- Anemia\n\n- Non-compliance with treatment\n\n- Non-compliance with dietary hygiene rules (low-salt diet deviation)",
  "question": {
    "question": "Which of the following is NOT a main cause of left heart failure?",
    "option_a": "Ischaemic heart disease",
    "option_b": "Chronic respiratory insufficiency",
    "option_c": "Valvular heart disease",
    "option_d": "Cardiomyopathy",
    "correct_option": "B"
  }
}