{
  "folder": "IC-315",
  "content": "{{knowledge objective\n|Identifiant=OIC-315-06-A\n|Item_parent=Acute leukaemia\n|Item_parent_short=Acute leukaemia\n|Rank=A\n|Title=Knowing how to identify the signs suggestive of the diagnosis of LA on the haemogram\n|Description=None\n|Topic=Positive diagnosis\n|Contributors=\n|Order=6}}\nThe blood count is always abnormal. It reflects bone marrow failure:\n\n- normo- or macrocytic anaemia, almost constant and sometimes severe\n\n- thrombocytopenia, almost constant and sometimes severe\n\n- neutropenia, almost constant and sometimes severe\n\n- circulating blasts, inconstant, may represent the majority of leukocytes",
  "question": {
    "question": "What is a characteristic of the blood count in acute leukaemia?",
    "option_a": "The blood count is always normal.",
    "option_b": "The blood count is always abnormal, reflecting bone marrow failure.",
    "option_c": "The blood count is only abnormal when there are circulating blasts.",
    "option_d": "The blood count is abnormal only in cases of severe anaemia."
  }
}